Chaff.py
chaff-0.0.6.dist-info/METADATA
chaff-0.0.6.dist-info/WHEEL
chaff-0.0.6.dist-info/top_level.txt
chaff-0.0.6.dist-info/RECORD
