Metadata-Version: 2.2
Name: Chaff
Version: 0.0.6
Summary: Chaff is a secure overwrite tool for permanent data destruction!
Author: Invizabel
Project-URL: Homepage, https://github.com/Invizabel/Chaff
Project-URL: Bug Tracker, https://github.com/Invizabel/Chaff
Classifier: Programming Language :: Python :: 3
Classifier: License :: OSI Approved :: MIT License
Classifier: Operating System :: OS Independent
Requires-Python: >=3.8
